updr/__init__.py
updr/cli.py
updr/symbols.py
upgrade_py_direct_reqs-0.2.4.dist-info/licenses/LICENSE
upgrade_py_direct_reqs-0.2.4.dist-info/METADATA
upgrade_py_direct_reqs-0.2.4.dist-info/WHEEL
upgrade_py_direct_reqs-0.2.4.dist-info/entry_points.txt
upgrade_py_direct_reqs-0.2.4.dist-info/top_level.txt
upgrade_py_direct_reqs-0.2.4.dist-info/RECORD
