Metadata-Version: 2.4
Name: upgrade-py-direct-reqs
Version: 0.2.4
Summary: Upgrade only direct dependencies in requirements.txt or pyproject.toml
Author-email: Miteshkumar Raval <mraval@nasagram.com>
Maintainer-email: Miteshkumar Raval <mraval@nasagram.com>
License-Expression: MIT
Project-URL: Homepage, https://github.com/mitesh-raval/upgrade-py-direct-reqs
Project-URL: Repository, https://github.com/mitesh-raval/upgrade-py-direct-reqs
Project-URL: Issues, https://github.com/mitesh-raval/upgrade-py-direct-reqs/issues
Keywords: dependencies,upgrades,upgrade packages,requirements upgrade
Classifier: Programming Language :: Python :: 3
Classifier: Operating System :: OS Independent
Classifier: Development Status :: 4 - Beta
Requires-Python: >=3.8
License-File: LICENSE
Requires-Dist: pip>=21.0
Requires-Dist: toml>=0.10.2
Provides-Extra: dev
Requires-Dist: pytest; extra == "dev"
Requires-Dist: twine; extra == "dev"
Dynamic: license-file
